[
    {
        "isNew": false,
        "id": 1,
        "name": "Tomate cerise 'Honeybee'",
        "latinName": "Lycopersicon esculentum",
        "family": "Solanacées",
        "plantingIn": "2016-12-03",
        "transplantOut": "2016-12-01",
        "directOut": "2016-12-07",
        "directGHSummer": "2016-12-06",
        "directGHWinter": "2016-12-20",
        "distanceBetweenPlants": 2,
        "distanceBetweenRows": 4,
        "yield": 10,
        "comment": "no comment 1",
        "coldHardy": false,
        "quantityOnHand": 15,
        "status": 1
    },
    {
        "isNew": false,
        "id": 2,
        "name": "Bette à carde 'Magenta sunset'",
        "latinName": "Beta vulgaris",
        "family": "Chénopodiacées",
        "plantingIn": "2015-12-06",
        "transplantOut": "2016-12-07",
        "directOut": "2016-12-22",
        "directGHSummer": "2016-12-17",
        "directGHWinter": "2016-12-09",
        "distanceBetweenPlants": 2,
        "distanceBetweenRows": 5,
        "yield": 10,
        "comment": "no comment 2",
        "coldHardy": true,
        "quantityOnHand": 57,
        "status": 1
    },
    {
        "isNew": false,
        "id": 3,
        "name": "Cerfeuil",
        "latinName": "Anthriscus cerefolium",
        "family": "Apiacées",
        "plantingIn": "2016-12-07",
        "transplantOut": "2016-12-07",
        "directOut": "2016-12-07",
        "directGHSummer": "2016-12-07",
        "directGHWinter": "2016-12-07",
        "distanceBetweenPlants": 2,
        "distanceBetweenRows": 6,
        "yield": 10,
        "comment": "no comment 3",
        "coldHardy": false,
        "quantityOnHand": 23,
        "status": 1
    },
    {
        "isNew": false,
        "id": 4,
        "name": "Piment oiseau",
        "latinName": "Capsicum frutescens",
        "family": "Solanacées",
        "plantingIn": "2016-12-07",
        "transplantOut": "2016-12-07",
        "directOut": "2016-12-07",
        "directGHSummer": "2016-12-07",
        "directGHWinter": "2016-12-07",
        "distanceBetweenPlants": 2,
        "distanceBetweenRows": 7,
        "yield": 10,
        "comment": "no comment 4",
        "coldHardy": false,
        "quantityOnHand": 42,
        "status": 1
    },
    {
        "isNew": false,
        "id": 5,
        "name": "Tatsoi",
        "latinName": "Brassica narinosa",
        "family": "Brassicaceae",
        "plantingIn": "2016-12-07",
        "transplantOut": "2016-12-07",
        "directOut": "2016-12-07",
        "directGHSummer": "2016-12-07",
        "directGHWinter": "2016-12-07",
        "distanceBetweenPlants": 2,
        "distanceBetweenRows": 8,
        "yield": 10,
        "comment": "no comment 5",
        "coldHardy": true,
        "quantityOnHand": 7,
        "status": 1
    }
]